{
  "versionCode": 441,
  "versionName": "1.44.41",
  "apkUrl": "https://hushtv.xyz/hushtv-official.apk",
  "mandatory": true,
  "releasedAt": "2026-05-07",
  "channel": "official",
  "changelog": [
    "First-run \"Choose your layout\" screen is gone — the app now opens directly into the canonical Left Sidebar layout for Live TV / Movies / Series. No setup steps, no friction.",
    "Carries over all v1.44.40 fixes — Dev and Official can install side-by-side for testing, distinct app icons, distinct labels (\"HushTV Official\" / \"HushTV Dev\")."
  ]
}
